s3_uncompress/__init_.py
s3_uncompress/exceptions.py
s3_uncompress/uncompress.py
s3_uncompress-0.1.0.dist-info/LICENSE
s3_uncompress-0.1.0.dist-info/METADATA
s3_uncompress-0.1.0.dist-info/WHEEL
s3_uncompress-0.1.0.dist-info/RECORD
