Metadata-Version: 2.1
Name: s3-uncompress
Version: 0.1.0
Summary: 
Author: Agustín Dalbesio
Author-email: agustindalbesio@gmail.com
Requires-Python: >=3.9,<4.0
Classifier: Programming Language :: Python :: 3
Classifier: Programming Language :: Python :: 3.9
Classifier: Programming Language :: Python :: 3.10
Classifier: Programming Language :: Python :: 3.11
Requires-Dist: boto3 (>=1.24.65,<2.0.0)
Requires-Dist: rarfile (>=4.0,<5.0)
